{
	"classes":	[{
			"name":	"EmptyDemo",
			"methods":	[{
					"name":	"<init>",
					"desc":	"()V",
					"args":	[],
					"returns":	"void",
					"code":	[{
							"name":	"aload_0",
							"data":	[],
							"pc":	0
						}, {
							"name":	"invokespecial",
							"data":	[0, 1],
							"pc":	1
						}, {
							"name":	"return",
							"data":	[],
							"pc":	4
						}]
				}, {
					"name":	"main",
					"desc":	"([Ljava/lang/String;)V",
					"args":	["java.lang.String[]"],
					"returns":	"void",
					"code":	[{
							"name":	"return",
							"data":	[],
							"pc":	0
						}]
				}],
			"constantPool":	[{
					"idx":	1,
					"tag":	10,
					"class_index":	3,
					"name_and_type_index":	17
				}, {
					"idx":	2,
					"tag":	7,
					"name_index":	18
				}, {
					"idx":	3,
					"tag":	7,
					"name_index":	19
				}, {
					"idx":	4,
					"tag":	1,
					"bytes":	"<init>"
				}, {
					"idx":	5,
					"tag":	1,
					"bytes":	"()V"
				}, {
					"idx":	6,
					"tag":	1,
					"bytes":	"Code"
				}, {
					"idx":	7,
					"tag":	1,
					"bytes":	"LineNumberTable"
				}, {
					"idx":	8,
					"tag":	1,
					"bytes":	"LocalVariableTable"
				}, {
					"idx":	9,
					"tag":	1,
					"bytes":	"this"
				}, {
					"idx":	10,
					"tag":	1,
					"bytes":	"LEmptyDemo;"
				}, {
					"idx":	11,
					"tag":	1,
					"bytes":	"main"
				}, {
					"idx":	12,
					"tag":	1,
					"bytes":	"([Ljava/lang/String;)V"
				}, {
					"idx":	13,
					"tag":	1,
					"bytes":	"args"
				}, {
					"idx":	14,
					"tag":	1,
					"bytes":	"[Ljava/lang/String;"
				}, {
					"idx":	15,
					"tag":	1,
					"bytes":	"SourceFile"
				}, {
					"idx":	16,
					"tag":	1,
					"bytes":	"EmptyDemo.java"
				}, {
					"idx":	17,
					"tag":	12,
					"name_index":	4,
					"descriptor_index":	5
				}, {
					"idx":	18,
					"tag":	1,
					"bytes":	"EmptyDemo"
				}, {
					"idx":	19,
					"tag":	1,
					"bytes":	"java/lang/Object"
				}],
			"fields":	[]
		}, {
			"name":	"java/lang/Object",
			"methods":	[{
					"name":	"<init>",
					"desc":	"()V",
					"args":	[],
					"returns":	"void",
					"code":	[{
							"name":	"return",
							"data":	[],
							"pc":	0
						}]
				}, {
					"name":	"equals",
					"desc":	"(Ljava/lang/Object;)Z",
					"args":	["java.lang.Object"],
					"returns":	"boolean",
					"code":	[{
							"name":	"aload_0",
							"data":	[],
							"pc":	0
						}, {
							"name":	"aload_1",
							"data":	[],
							"pc":	1
						}, {
							"name":	"if_acmpne",
							"data":	[0, 7],
							"pc":	2
						}, {
							"name":	"iconst_1",
							"data":	[],
							"pc":	5
						}, {
							"name":	"goto",
							"data":	[0, 4],
							"pc":	6
						}, {
							"name":	"iconst_0",
							"data":	[],
							"pc":	9
						}, {
							"name":	"ireturn",
							"data":	[],
							"pc":	10
						}]
				}, {
					"name":	"getDataAddress",
					"desc":	"(Ljava/lang/Object;)I",
					"args":	["java.lang.Object"],
					"returns":	"int",
					"code":	[]
				}, {
					"name":	"hashCode",
					"desc":	"()I",
					"args":	[],
					"returns":	"int",
					"code":	[{
							"name":	"aload_0",
							"data":	[],
							"pc":	0
						}, {
							"name":	"invokestatic",
							"data":	[0, 1],
							"pc":	1
						}, {
							"name":	"ireturn",
							"data":	[],
							"pc":	4
						}]
				}, {
					"name":	"notify",
					"desc":	"()V",
					"args":	[],
					"returns":	"void",
					"code":	[]
				}, {
					"name":	"notifyAll",
					"desc":	"()V",
					"args":	[],
					"returns":	"void",
					"code":	[]
				}, {
					"name":	"wait",
					"desc":	"()V",
					"args":	[],
					"returns":	"void",
					"code":	[]
				}, {
					"name":	"wait",
					"desc":	"(J)V",
					"args":	["long"],
					"returns":	"void",
					"code":	[]
				}, {
					"name":	"toString",
					"desc":	"()Ljava/lang/String;",
					"args":	[],
					"returns":	"java.lang.String",
					"code":	[{
							"name":	"ldc",
							"data":	[2],
							"pc":	0
						}, {
							"name":	"areturn",
							"data":	[],
							"pc":	2
						}]
				}, {
					"name":	"getClass",
					"desc":	"()Ljava/lang/Class;",
					"args":	[],
					"returns":	"java.lang.Class",
					"code":	[{
							"name":	"aconst_null",
							"data":	[],
							"pc":	0
						}, {
							"name":	"areturn",
							"data":	[],
							"pc":	1
						}]
				}],
			"constantPool":	[{
					"idx":	1,
					"tag":	10,
					"class_index":	3,
					"name_and_type_index":	24
				}, {
					"idx":	2,
					"tag":	8,
					"string_index":	25
				}, {
					"idx":	3,
					"tag":	7,
					"name_index":	26
				}, {
					"idx":	4,
					"tag":	1,
					"bytes":	"<init>"
				}, {
					"idx":	5,
					"tag":	1,
					"bytes":	"()V"
				}, {
					"idx":	6,
					"tag":	1,
					"bytes":	"Code"
				}, {
					"idx":	7,
					"tag":	1,
					"bytes":	"equals"
				}, {
					"idx":	8,
					"tag":	1,
					"bytes":	"(Ljava/lang/Object;)Z"
				}, {
					"idx":	9,
					"tag":	1,
					"bytes":	"StackMapTable"
				}, {
					"idx":	10,
					"tag":	1,
					"bytes":	"getDataAddress"
				}, {
					"idx":	11,
					"tag":	1,
					"bytes":	"(Ljava/lang/Object;)I"
				}, {
					"idx":	12,
					"tag":	1,
					"bytes":	"hashCode"
				}, {
					"idx":	13,
					"tag":	1,
					"bytes":	"()I"
				}, {
					"idx":	14,
					"tag":	1,
					"bytes":	"notify"
				}, {
					"idx":	15,
					"tag":	1,
					"bytes":	"notifyAll"
				}, {
					"idx":	16,
					"tag":	1,
					"bytes":	"wait"
				}, {
					"idx":	17,
					"tag":	1,
					"bytes":	"Exceptions"
				}, {
					"idx":	18,
					"tag":	7,
					"name_index":	27
				}, {
					"idx":	19,
					"tag":	1,
					"bytes":	"(J)V"
				}, {
					"idx":	20,
					"tag":	1,
					"bytes":	"toString"
				}, {
					"idx":	21,
					"tag":	1,
					"bytes":	"()Ljava/lang/String;"
				}, {
					"idx":	22,
					"tag":	1,
					"bytes":	"getClass"
				}, {
					"idx":	23,
					"tag":	1,
					"bytes":	"()Ljava/lang/Class;"
				}, {
					"idx":	24,
					"tag":	12,
					"name_index":	10,
					"descriptor_index":	11
				}, {
					"idx":	25,
					"tag":	1,
					"bytes":	"<Object>"
				}, {
					"idx":	26,
					"tag":	1,
					"bytes":	"java/lang/Object"
				}, {
					"idx":	27,
					"tag":	1,
					"bytes":	"java/lang/InterruptedException"
				}],
			"fields":	[]
		}],
	"instructions":	[{
			"diff":	[{
					"operation":	"PUSH_STACK_FRAME",
					"locals":	1,
					"method":	"main",
					"class":	"EmptyDemo",
					"arguments":	[{
							"type":	"object",
							"value":	6656256,
							"index":	0
						}]
				}],
			"PC":	null,
			"methodName":	null,
			"methodDesc":	null,
			"class":	null
		}, {
			"PC":	0,
			"methodName":	"main",
			"methodDesc":	"([Ljava/lang/String;)V",
			"class":	"EmptyDemo",
			"diff":	[{
					"operation":	"POP_STACK_FRAME"
				}]
		}]
}